[
	{
		"title": "Notebook Lenovo",
		"description": "Notebook Lenovo última generación",
		"price": 2000,
		"thumbnail": "",
		"code": "notebook-001",
		"stock": 250,
		"id": 1
	},
	{
		"title": "HP Omen 16",
		"description": "Notebook HP Omen 16",
		"price": 2500,
		"thumbnail": "",
		"code": "notebook-002",
		"stock": 250,
		"id": 2
	},
	{
		"title": "Asus TUF Gaming",
		"description": "Notebook Asus TUF Gaming año 2020",
		"price": 2200,
		"thumbnail": "",
		"code": "notebook-003",
		"stock": 250,
		"id": 3
	}

]